<?xml version="1.0" encoding="utf-8"?><toc><breadcrumbs><li><a href="3300965f-9c80-0a9a-5861-f1d094b98294.htm">Docs</a></li><li><a href="c158b235-d02d-f550-70d5-f52756599c96.htm">Assignment<wbr />1.<wbr />Command<wbr />Handler.<wbr />Impl</a></li><li><a href="bfb3c5f0-1df3-6e08-01a2-ba55f5feee9f.htm">While<wbr />Handler</a></li></breadcrumbs><tocItems><li><a id="d9b4bcca-879f-8fa1-dd1b-8d340f80da05" href="d9b4bcca-879f-8fa1-dd1b-8d340f80da05.htm">Constructor</a></li><li><a id="8d6c133f-b98c-b93f-4954-b60e47d1beb9" class="has-submenu" href="8d6c133f-b98c-b93f-4954-b60e47d1beb9.htm"><span data-tocFile="../toc/IDBOC.xml" class="icon toggle" onclick="ToggleExpandCollapse(this); return false;"><i class="fa fa-angle-right"> </i></span>Methods</a><ul class="toc-menu is-hidden"> </ul></li><li><a id="61a8643d-9225-b9be-345e-62442b4c6d67" class="has-submenu" href="61a8643d-9225-b9be-345e-62442b4c6d67.htm"><span data-tocFile="../toc/IDCOC.xml" class="icon toggle" onclick="ToggleExpandCollapse(this); return false;"><i class="fa fa-angle-right"> </i></span>Fields</a><ul class="toc-menu is-hidden"> </ul></li></tocItems></toc>